aemet_mcp/__init__.py
aemet_mcp/server.py
aemet_mcp/res/Beaches_code.json
aemet_mcp/res/Municipallity_code.json
aemet_mcp/res/Provinces_code.json
aemet_mcp/res/Stations_code.json
mseep_aemet_mcp-0.2.3.dist-info/licenses/LICENSE
mseep_aemet_mcp-0.2.3.dist-info/METADATA
mseep_aemet_mcp-0.2.3.dist-info/WHEEL
mseep_aemet_mcp-0.2.3.dist-info/entry_points.txt
mseep_aemet_mcp-0.2.3.dist-info/top_level.txt
mseep_aemet_mcp-0.2.3.dist-info/RECORD
